ovpn_tls_crypt_v2_generator/__init__.py
ovpn_tls_crypt_v2_generator-1.0.1.dist-info/licenses/LICENSE
ovpn_tls_crypt_v2_generator-1.0.1.dist-info/METADATA
ovpn_tls_crypt_v2_generator-1.0.1.dist-info/WHEEL
ovpn_tls_crypt_v2_generator-1.0.1.dist-info/entry_points.txt
ovpn_tls_crypt_v2_generator-1.0.1.dist-info/top_level.txt
ovpn_tls_crypt_v2_generator-1.0.1.dist-info/RECORD
