Metadata-Version: 2.4
Name: ovpn-tls-crypt-v2-generator
Version: 1.0.1
Summary: Text Blob and Object Dumper
Author-email: Aaron Edwards <openvpn_tls_crypt_v2_keygen@ebob9.com>
Project-URL: Homepage, https://github.com/ebob9/openvpn_tls_crypt_v2_keygen
Requires-Python: >=3.11
License-File: LICENSE
Dynamic: license-file
